general/__init__.py
general/common.py
qm_scripts-0.1.1.data/scripts/xyz2pdb.py
qm_scripts-0.1.1.data/scripts/xyz2psf.py
qm_scripts-0.1.1.dist-info/DESCRIPTION.rst
qm_scripts-0.1.1.dist-info/METADATA
qm_scripts-0.1.1.dist-info/RECORD
qm_scripts-0.1.1.dist-info/WHEEL
qm_scripts-0.1.1.dist-info/metadata.json
qm_scripts-0.1.1.dist-info/top_level.txt
